egglog-12.0.0.dist-info/METADATA
egglog-12.0.0.dist-info/WHEEL
egglog-12.0.0.dist-info/licenses/LICENSE
egglog/__init__.py
egglog/bindings.cpython-313-powerpc64-linux-gnu.so
egglog/bindings.pyi
egglog/builtins.py
egglog/config.py
egglog/conversion.py
egglog/declarations.py
egglog/deconstruct.py
egglog/egraph.py
egglog/egraph_state.py
egglog/examples/README.rst
egglog/examples/__init__.py
egglog/examples/bignum.py
egglog/examples/bool.py
egglog/examples/eqsat_basic.py
egglog/examples/fib.py
egglog/examples/higher_order_functions.py
egglog/examples/jointree.py
egglog/examples/lambda_.py
egglog/examples/matrix.py
egglog/examples/multiset.py
egglog/examples/ndarrays.py
egglog/examples/resolution.py
egglog/examples/schedule_demo.py
egglog/exp/MoA.ipynb
egglog/exp/__init__.py
egglog/exp/any_expr.py
egglog/exp/any_expr_example.ipynb
egglog/exp/array_api.py
egglog/exp/array_api_jit.py
egglog/exp/array_api_loopnest.py
egglog/exp/array_api_numba.py
egglog/exp/array_api_program_gen.py
egglog/exp/program_gen.py
egglog/exp/siu_examples.py
egglog/ipython_magic.py
egglog/pretty.py
egglog/py.typed
egglog/runtime.py
egglog/thunk.py
egglog/type_constraint_solver.py
egglog/visualizer.css
egglog/visualizer.js
egglog/visualizer_widget.py
egglog-12.0.0.dist-info/RECORD
