Metadata-Version: 2.4
Name: egglog
Version: 12.0.0
Classifier: Environment :: MacOS X
Classifier: Environment :: Win32 (MS Windows)
Classifier: Intended Audience :: Developers
Classifier: License :: OSI Approved :: MIT License
Classifier: Natural Language :: English
Classifier: Programming Language :: Python :: 3
Classifier: Programming Language :: Python :: 3.11
Classifier: Programming Language :: Python :: 3.12
Classifier: Programming Language :: Python :: 3.13
Classifier: Programming Language :: Rust
Classifier: Programming Language :: Python :: Implementation :: CPython
Classifier: Programming Language :: Python :: Implementation :: PyPy
Classifier: Topic :: Software Development :: Compilers
Classifier: Topic :: Software Development :: Interpreters
Classifier: Typing :: Typed
Requires-Dist: typing-extensions
Requires-Dist: black
Requires-Dist: graphviz
Requires-Dist: anywidget
Requires-Dist: scikit-learn ; extra == 'array'
Requires-Dist: array-api-compat ; extra == 'array'
Requires-Dist: numba>=0.59.1 ; extra == 'array'
Requires-Dist: llvmlite>=0.42.0 ; extra == 'array'
Requires-Dist: numpy>2 ; extra == 'array'
Requires-Dist: cloudpickle>=3 ; extra == 'array'
Requires-Dist: ruff ; extra == 'dev'
Requires-Dist: pre-commit ; extra == 'dev'
Requires-Dist: mypy ; extra == 'dev'
Requires-Dist: anywidget[dev] ; extra == 'dev'
Requires-Dist: egglog[docs,test] ; extra == 'dev'
Requires-Dist: jupyterlab ; extra == 'dev'
Requires-Dist: ipykernel ; extra == 'dev'
Requires-Dist: pytest ; extra == 'test'
Requires-Dist: mypy ; extra == 'test'
Requires-Dist: syrupy>=5 ; extra == 'test'
Requires-Dist: egglog[array] ; extra == 'test'
Requires-Dist: pytest-codspeed ; extra == 'test'
Requires-Dist: pytest-benchmark ; extra == 'test'
Requires-Dist: pytest-xdist ; extra == 'test'
Requires-Dist: pydata-sphinx-theme ; extra == 'docs'
Requires-Dist: myst-nb ; extra == 'docs'
Requires-Dist: sphinx-autodoc-typehints ; extra == 'docs'
Requires-Dist: sphinx-gallery ; extra == 'docs'
Requires-Dist: nbconvert ; extra == 'docs'
Requires-Dist: matplotlib ; extra == 'docs'
Requires-Dist: anywidget ; extra == 'docs'
Requires-Dist: seaborn ; extra == 'docs'
Requires-Dist: egglog[array] ; extra == 'docs'
Requires-Dist: line-profiler ; extra == 'docs'
Requires-Dist: sphinxcontrib-mermaid ; extra == 'docs'
Requires-Dist: ablog ; extra == 'docs'
Requires-Dist: jupytext ; extra == 'docs'
Provides-Extra: array
Provides-Extra: dev
Provides-Extra: test
Provides-Extra: docs
License-File: LICENSE
Summary: e-graphs in Python built around the the egglog rust library
License: MIT
Requires-Python: >=3.11
